hyperon_das_node/__init__.py
hyperon_das_node/hyperon_das_node_ext.so
hyperon_das_node-0.10.1.dist-info/WHEEL
hyperon_das_node-0.10.1.dist-info/METADATA
hyperon_das_node-0.10.1.dist-info/RECORD
